ai_music_remixer/__init__.py
ai_music_remixer/cli.py
ai_music_remixer/remixer.py
ai_music_remixer/neural/__init__.py
ai_music_remixer/neural/train_transition.py
ai_music_remixer/neural/transition_model.py
ai_music_remixer/neural/utils.py
ai_music_remixer-3.0.0.dist-info/METADATA
ai_music_remixer-3.0.0.dist-info/WHEEL
ai_music_remixer-3.0.0.dist-info/top_level.txt
ai_music_remixer-3.0.0.dist-info/RECORD
