Metadata-Version: 2.4
Name: ai_music_remixer
Version: 3.0.0
Summary: AI-powered intelligent music remixer with optional neural transitions
Author: YourName
Author-email: you@example.com
Requires-Python: >=3.8
Requires-Dist: pydub
Requires-Dist: librosa
Requires-Dist: soundfile
Requires-Dist: spleeter
Requires-Dist: numpy
Requires-Dist: scipy
